workflowai/__init__.py
workflowai/core/__init__.py
workflowai/core/_common_types.py
workflowai/core/_logger.py
workflowai/core/client/__init__.py
workflowai/core/client/_api.py
workflowai/core/client/_fn_utils.py
workflowai/core/client/_models.py
workflowai/core/client/_types.py
workflowai/core/client/_utils.py
workflowai/core/client/agent.py
workflowai/core/client/client.py
workflowai/core/domain/__init__.py
workflowai/core/domain/cache_usage.py
workflowai/core/domain/completion.py
workflowai/core/domain/errors.py
workflowai/core/domain/model.py
workflowai/core/domain/run.py
workflowai/core/domain/task.py
workflowai/core/domain/tool.py
workflowai/core/domain/tool_call.py
workflowai/core/domain/version.py
workflowai/core/domain/version_properties.py
workflowai/core/domain/version_reference.py
workflowai/core/fields/__init__.py
workflowai/core/fields/audio.py
workflowai/core/fields/chat_message.py
workflowai/core/fields/email_address.py
workflowai/core/fields/file.py
workflowai/core/fields/html_string.py
workflowai/core/fields/http_url.py
workflowai/core/fields/image.py
workflowai/core/fields/local_date_time.py
workflowai/core/fields/pdf.py
workflowai/core/fields/price.py
workflowai/core/fields/surface_area.py
workflowai/core/fields/zone_info.py
workflowai/core/utils/__init__.py
workflowai/core/utils/_iter.py
workflowai/core/utils/_pydantic.py
workflowai/core/utils/_schema_generator.py
workflowai/core/utils/_tools.py
workflowai/core/utils/_vars.py
workflowai/env.py
workflowai/fields.py
workflowai/py.typed
workflowai-0.6.10.dist-info/LICENSE
workflowai-0.6.10.dist-info/METADATA
workflowai-0.6.10.dist-info/WHEEL
workflowai-0.6.10.dist-info/entry_points.txt
workflowai-0.6.10.dist-info/RECORD
