Metadata-Version: 2.1
Name: workflowai
Version: 0.6.10
Summary: Python SDK for WorkflowAI
Author: Guillaume Aquilina
Author-email: guillaume@workflowai.com
Requires-Python: >=3.9,<4.0
Classifier: Programming Language :: Python :: 3
Classifier: Programming Language :: Python :: 3.9
Classifier: Programming Language :: Python :: 3.10
Classifier: Programming Language :: Python :: 3.11
Classifier: Programming Language :: Python :: 3.12
Requires-Dist: httpx (>=0.27)
Requires-Dist: pydantic (>=2.7.4)
